collective.checklist-0.1a3-py3.13-nspkg.pth
collective/checklist/__init__.py
collective/checklist/configure.zcml
collective/checklist/interfaces.py
collective/checklist/permissions.zcml
collective/checklist/setuphandlers.py
collective/checklist/testing.py
collective/checklist/apps/svecklist/svecklist-main.js
collective/checklist/apps/svecklist/svecklist-main.js.map
collective/checklist/apps/svecklist/vite.svg
collective/checklist/apps/svecklist/.vite/manifest.json
collective/checklist/browser/__init__.py
collective/checklist/browser/configure.zcml
collective/checklist/browser/overrides/.gitkeep
collective/checklist/browser/static/.gitkeep
collective/checklist/browser/static/checklist-widget.js
collective/checklist/content/__init__.py
collective/checklist/content/checklist.py
collective/checklist/locales/README.rst
collective/checklist/locales/__init__.py
collective/checklist/locales/collective.checklist.pot
collective/checklist/locales/update.py
collective/checklist/locales/update.sh
collective/checklist/locales/en/LC_MESSAGES/collective.checklist.po
collective/checklist/profiles/default/browserlayer.xml
collective/checklist/profiles/default/catalog.xml
collective/checklist/profiles/default/metadata.xml
collective/checklist/profiles/default/rolemap.xml
collective/checklist/profiles/default/types.xml
collective/checklist/profiles/default/registry/main.xml
collective/checklist/profiles/default/types/Checklist.xml
collective/checklist/profiles/uninstall/browserlayer.xml
collective/checklist/tests/__init__.py
collective/checklist/tests/test_ct_checklist.py
collective/checklist/tests/test_robot.py
collective/checklist/tests/test_setup.py
collective/checklist/tests/test_view_checklist_view.py
collective/checklist/tests/robot/test_ct_checklist.robot
collective/checklist/tests/robot/test_example.robot
collective/checklist/views/__init__.py
collective/checklist/views/checklist_view.pt
collective/checklist/views/checklist_view.py
collective/checklist/views/configure.zcml
collective_checklist-0.1a3.dist-info/licenses/LICENSE.GPL
collective_checklist-0.1a3.dist-info/licenses/LICENSE.rst
collective_checklist-0.1a3.dist-info/METADATA
collective_checklist-0.1a3.dist-info/WHEEL
collective_checklist-0.1a3.dist-info/entry_points.txt
collective_checklist-0.1a3.dist-info/namespace_packages.txt
collective_checklist-0.1a3.dist-info/top_level.txt
collective_checklist-0.1a3.dist-info/RECORD
